{
  "schema": "gtcx://canon-os/gtm-readiness-witness/v1",
  "repo": "ecosystem-os",
  "generatedAt": "2026-06-23T14:33:29.815Z",
  "profile": "product",
  "dimensions": [
    {
      "id": "pillars11pr",
      "score": 59,
      "pass": true
    },
    {
      "id": "roadmapHierarchy",
      "score": 100,
      "pass": true
    },
    {
      "id": "forensicSpecs",
      "score": 68.8,
      "pass": false
    },
    {
      "id": "readinessStatus",
      "score": 85,
      "pass": true
    },
    {
      "id": "backlogPopulation",
      "score": 75,
      "pass": true
    },
    {
      "id": "reportsAvailable",
      "score": 100,
      "pass": true
    }
  ],
  "pass": false
}
